Metadata-Version: 1.0
Name: distributions1307
Version: 0.1
Summary: Gaussian and Binomial distributions
Home-page: UNKNOWN
Author: Alexander Julius Wolters
Author-email: alexander.woltersgo@gmail.com
License: UNKNOWN
Platform: UNKNOWN
